<?xml version="1.0" encoding="UTF-8"?>
<ROWSET>
<ROW>
<SUPNBR>H000000106</SUPNBR>
<CTRNBR>17</CTRNBR>
<CTRNBR_1>1212</CTRNBR_1>
<AGT_CD>NTA</AGT_CD>
<SUPNM1><![CDATA[AKAKURA HOTEL]]></SUPNM1>
<JPNNAM><![CDATA[赤倉ホテル]]></JPNNAM>
<SUPAD1/>
<SUPAD2>新潟県 中頚城郡妙高高原町赤倉</SUPAD2>
<SUPAD3/>
<PROMISE/>
<PROMISEURI/>
<SUPTEL>0255-87-2001</SUPTEL>
<SUPFAX>0255-87-2033</SUPFAX>
<JPNTXT/>
<HTLTYP>3</HTLTYP>
<HTLCAT/>
<HRLLOC/>
<APTCDE/>
<APTDST/>
<HTLRST/>
<HTLBTH>1</HTLBTH>
<HTLAIR/>
<HTLCFR>1</HTLCFR>
<CFRMAX>350</CFRMAX>
<HTLBQT>1</HTLBQT>
<BQTMAX>350</BQTMAX>
<HTLPKG>3</HTLPKG>
<ARECTR/>
<ARECTY/>
<AREDIS/>
<HTLEST>1716</HTLEST>
<HTLRNV/>
<HTLRMS>68</HTLRMS>
<SUTRMS/>
<TWNRMS/>
<DBLRMS/>
<SGLRMS/>
<CARD1>1</CARD1>
<CARD2>0</CARD2>
<CARD3>1</CARD3>
<CARD4>0</CARD4>
<CARD5>1</CARD5>
<CARD6>1</CARD6>
<CARDNM>UC</CARDNM>
<NERSTN>信越本線 妙高高原駅より車13分</NERSTN>
<ACSPNT/>
<FARCTY/>
<RSPNUM>0255-87-2001</RSPNUM>
<RSFNUM>0255-87-2033</RSFNUM>
<HEMAIL>ah2001@lily.ocn.ne.jp</HEMAIL>
<WEBADD>http://www1.ocn.ne.jp/~akakura/</WEBADD>
<OFCCAT>0</OFCCAT>
<FLRNUM/>
<ELEVTR/>
<ELECAP/>
<LSTRFB/>
<RNVSTR/>
<RNVEND/>
<RNVDTL/>
<TRAFICXML/>
<GRPCHK/>
<CHECKINXML/>
<LANENG/>
<LANJAP>O</LANJAP>
<LANGXML/>
<PHNR2R/>
<PHONEXML/>
<SERVICEXML/>
<TOTRST>3</TOTRST>
<TOTBAR/>
<TOTCON>2</TOTCON>
<IMGFRN/>
<IMGLOB/>
<IMGROM/>
<BUILDXML/>
<MNTRMS>68</MNTRMS>
<TOTANR/>
<SGLTOT/>
<SINGLEXML/>
<TWNTOT/>
<TWINXML/>
<DBFTOT/>
<DOUBLEXML/>
<DBGTOT/>
<DOUBLEGXML/>
<TPLTOT/>
<TRIPLEXML/>
<QADTOT/>
<QADTOTXML/>
<FAMTOT/>
<FAMILYXML/>
<EXETOT/>
<SUPTOT/>
<DLXTOT/>
<OTHTOT/>
<OTHRNM/>
<JNRSUT/>
<STDSUT/>
<DLXSUT/>
<PRSSUT/>
<OTHSUT/>
<OTHSNM/>
<NONRMS/>
<NONFLR/>
<WHLACS/>
<DSLRMS/>
<DSLSIZ/>
<DSLBAT/>
<DSLTWN/>
<DSLDBL/>
<DSLSGL/>
<DSLTPL/>
<DSLTSU/>
<DSLRDW/>
<DSLBD/>
</ROW>
</ROWSET>
